govcf/__init__.py
govcf/bed_filter.py
govcf/variant_files.py
govcf/calculate_vaf/__init__.py
govcf/calculate_vaf/ad_rd_dp.py
govcf/calculate_vaf/ao_ro_dp.py
govcf/calculate_vaf/base.py
govcf/calculate_vaf/brli.py
govcf/calculate_vaf/clcbio.py
govcf/calculate_vaf/fao_fdp.py
govcf/calculate_vaf/pheo.py
govcf/calculate_vaf/strelka.py
govcf/calculate_vaf/usc.py
govcf/calculate_vaf/utils.py
govcf-0.10.0.dist-info/METADATA
govcf-0.10.0.dist-info/WHEEL
govcf-0.10.0.dist-info/top_level.txt
govcf-0.10.0.dist-info/RECORD
