Metadata-Version: 2.4
Name: govcf
Version: 0.10.0
Summary: govcf
Author-email: Ian Maurer <ian@genomoncology.com>
Classifier: Development Status :: 4 - Beta
Classifier: Intended Audience :: Developers
Classifier: License :: Other/Proprietary License
Classifier: Natural Language :: English
Classifier: Programming Language :: Python
Classifier: Programming Language :: Python :: 3.13
Classifier: Topic :: Scientific/Engineering :: Bio-Informatics
Requires-Python: >=3.13
Requires-Dist: pysam>=0.23.3
Requires-Dist: intervaltree
Requires-Dist: pydantic>=2.0.0
